AUTHORS.rst
CONTRIBUTING.rst
HISTORY.rst
LICENSE
MANIFEST.in
README.rst
requirements.txt
setup.cfg
setup.py
docs/Makefile
docs/authors.rst
docs/conf.py
docs/contributing.rst
docs/history.rst
docs/index.rst
docs/installation.rst
docs/make.bat
docs/readme.rst
docs/usage.rst
quickbook3/__init__.py
quickbook3/auth.py
quickbook3/exceptions.py
quickbook3/querybuilder.py
quickbook3/quickbook.py
quickbook3/response.py
quickbooks_py.egg-info/PKG-INFO
quickbooks_py.egg-info/SOURCES.txt
quickbooks_py.egg-info/dependency_links.txt
quickbooks_py.egg-info/not-zip-safe
quickbooks_py.egg-info/pbr.json
quickbooks_py.egg-info/requires.txt
quickbooks_py.egg-info/top_level.txt
tests/__init__.py
tests/test_querybuilder.py
tests/test_quickbooks.py
tests/test_response.py
tests/utils.py
tests/fixtures/credfile
tests/fixtures/incomplete_credfile